{
  "os":  "Linux-6.8.0-59-generic-x86_64-with-glibc2.35",
  "python":  "CPython 3.11.0rc1",
  "startedAt":  "2025-08-07T16:11:28.687225Z",
  "program":  "workspace/cnn_cancer_detection_template 5.ipynb",
  "git":  {
    "remote":  "git@github.com:tgrytnes/cnn-cancer-detection.git",
    "commit":  "4d7ab22a7f1383e962be73ac2155839b43c28e38"
  },
  "email":  "thomas.grytnes+m8xa7mfr@posteo.net",
  "root":  "/workspace",
  "host":  "f4ae2c7bf021",
  "executable":  "/usr/bin/python3",
  "cpu_count":  48,
  "cpu_count_logical":  96,
  "gpu":  "NVIDIA A40",
  "gpu_count":  1,
  "disk":  {
    "/":  {
      "total":  "21474836480",
      "used":  "1269604352"
    }
  },
  "memory":  {
    "total":  "540644179968"
  },
  "gpu_nvidia":  [
    {
      "name":  "NVIDIA A40",
      "memoryTotal":  "48305799168",
      "cudaCores":  10752,
      "architecture":  "Ampere",
      "uuid":  "GPU-ba32065c-329e-b7e0-b778-e53670be6cfc"
    }
  ],
  "cudaVersion":  "12.7",
  "writerId":  "grm8j2uwgv7jh1pl8qfiriojfehje6in"
}